Full_Adder/Full_Adder_4bit/half_adder.v
module half_adder(
    input a,
    input b,
    output sum,
    output carry
);
    
    // Logic for sum (XOR operation)
    assign sum = a ^ b;
    
    // Logic for carry (AND operation)
    assign carry = a & b;
    
endmodule

Full_Adder/Full_Adder_32bit/full_adder_1bit.v
module full_adder_1bit(
	input a,
	input b,
	input cin,
	output sum,
	output cout
);
	wire sum1;
	wire carry1;
	wire carry2;
	
	half_adder ha1(
               .a(a),
		       .b(b),
		       .sum(sum1),
		       .carry(carry1)
	);
	
	half_adder ha2(
               .a(sum1),
		       .b(cin),
		       .sum(sum),
		       .carry(carry2) 		
	);

	assign cout = carry1 | carry2;
endmodule

Full_Adder/Full_Adder_8bit/full_adder_8bit.v
/* module full_adder_8bit(
    input [7:0] a,
    input [7:0] b,
    input cin,
    output [7:0] sum,
    output cout,
    output overflow
);
    wire sum1;
    wire sum2;
    wire sum3;
    wire sum4;
    wire sum5;
    wire sum6;
    wire sum7;
    wire sum8;
    wire carry1;
    wire carry2;
    wire carry3;
    wire carry4;
    wire carry5;
    wire carry6;
    wire carry7;
    wire carry8;

    full_adder_1bit fa1(
        .a(a[0]),
        .b(b[0]),
        .cin(cin),
        .sum(sum[0]),
        .cout(carry1)
    );

    full_adder_1bit fa2(
        .a(a[1]),
        .b(b[1]),
        .cin(carry1),
        .sum(sum[1]),
        .cout(carry2)
    );

    full_adder_1bit fa3(
        .a(a[2]),
        .b(b[2]),
        .cin(carry2),
        .sum(sum[2]),
        .cout(carry3)
    );

    full_adder_1bit fa4(
        .a(a[3]),
        .b(b[3]),
        .cin(carry3),
        .sum(sum[3]),
        .cout(carry4)
    );

    full_adder_1bit fa5(
        .a(a[4]),
        .b(b[4]),
        .cin(carry4),
        .sum(sum[4]),
        .cout(carry5)
    );

    full_adder_1bit fa6(
        .a(a[5]),
        .b(b[5]),
        .cin(carry5),
        .sum(sum[5]),
        .cout(carry6)
    );

    full_adder_1bit fa7(
        .a(a[6]),
        .b(b[6]),
        .cin(carry6),
        .sum(sum[6]),
        .cout(carry7)
    );

    full_adder_1bit fa8(
        .a(a[7]),   
        .b(b[7]),
        .cin(carry7),
        .sum(sum[7]),
        .cout(cout)
    );

    // Overflow xảy ra khi hai số cùng dấu nhưng kết quả khác dấu
    // Đối với số có dấu (signed numbers)
    assign overflow = (a[7] == b[7]) && (a[7] != sum[7]);
endmodule

*/

module full_adder_8bit(
    input [7:0] a,
    input [7:0] b,
    input cin,
    output [7:0] sum,
    output cout,
    output overflow
);
    wire [8:0] carry;
    assign carry[0] = cin;
    assign cout = carry[8];

    genvar i;
    generate 
        for (i = 0; i < 8; i = i + 1) begin : full_adder_loop
            full_adder_1bit fa (
                .a(a[i]),
                .b(b[i]),
                .cin(carry[i]),
                .sum(sum[i]),
                .cout(carry[i+1])
            );
        end
    endgenerate

    assign overflow = (a[7] == b[7]) && (a[7] != sum[7]);
endmodule

Full_Adder/Full_Adder_8bit/full_adder_8bit_tb.v
module full_adder_8bit_tb;
    // Inputs
    reg [7:0] a;
    reg [7:0] b;
    reg cin;
    
    // Outputs
    wire [7:0] sum;
    wire cout;
    wire overflow;
    
    // Biến phụ để hiển thị số có dấu
    reg signed [7:0] a_signed;
    reg signed [7:0] b_signed;
    wire signed [7:0] sum_signed;
    
    // Instantiate the Unit Under Test (UUT)
    full_adder_8bit uut (
        .a(a),
        .b(b),
        .cin(cin),
        .sum(sum),
        .cout(cout),
        .overflow(overflow)
    );
    
    // Gán giá trị cho biến phụ
    always @* begin
        a_signed = a;
        b_signed = b;
    end
    
    assign sum_signed = sum;
    
    initial begin
        // Initialize inputs
        a = 0; b = 0; cin = 0;
        #10;
        
        // Test case 1: Simple addition (không tràn số)
        a = 8'h05; b = 8'h0A; cin = 0; // 5 + 10 = 15
        #10;
        
        // Test case 2: Addition with carry-in
        a = 8'h05; b = 8'h0A; cin = 1; // 5 + 10 + 1 = 16
        #10;
        
        // Test case 3: Larger numbers (không tràn số)
        a = 8'h3F; b = 8'h40; cin = 0; // 63 + 64 = 127 (max positive signed)
        #10;
        
        // Test case 4: Overflow dương (hai số dương ra số âm)
        a = 8'h7F; b = 8'h01; cin = 0; // 127 + 1 = 128 (overflow, kết quả là -128)
        #10;
        
        // Test case 5: Overflow âm (hai số âm ra số dương)
        a = 8'h80; b = 8'h80; cin = 0; // -128 + -128 = -256 (overflow, kết quả là 0 với cout=1)
        #10;
        
        // Test case 6: Số âm + số dương = số âm (không overflow)
        a = 8'hFF; b = 8'h01; cin = 0; // -1 + 1 = 0
        #10;
        
        // Test case 7: Số âm + số dương = số dương (không overflow)
        a = 8'hFF; b = 8'h02; cin = 0; // -1 + 2 = 1
        #10;
        
        // Test case 8: Số âm + số âm (không overflow)
        a = 8'hFE; b = 8'hFD; cin = 0; // -2 + -3 = -5
        #10;
        
        // Test case 9: Carry out nhưng không overflow
        a = 8'hFF; b = 8'h01; cin = 0; // 255 + 1 = 256 (cout=1, sum=0) hoặc -1 + 1 = 0 (không overflow)
        #10;
        
        // Test case 10: Maximum unsigned value
        a = 8'hFF; b = 8'hFF; cin = 0; // 255 + 255 = 510 (cout=1, sum=FE)
        #10;
        
        $finish;
    end
    
    // Display results
    initial begin
        $monitor("Time=%0t | a=%h(%0d/%0d) b=%h(%0d/%0d) cin=%b | sum=%h(%0d/%0d) cout=%b overflow=%b", 
                 $time, a, a, a_signed, b, b, b_signed, cin, sum, sum, sum_signed, cout, overflow);
        $dumpfile("full_adder_8bit_tb.vcd");
        $dumpvars(0, full_adder_8bit_tb);
    end
endmodule

Full_Adder/Full_Adder_8bit/full_adder_8bit_tb.vcd
$date
	Mon Jun 23 14:40:31 2025
$end
$version
	Icarus Verilog
$end
$timescale
	1s
$end
$scope module full_adder_8bit_tb $end
$var wire 8 ! sum_signed [7:0] $end
$var wire 8 " sum [7:0] $end
$var wire 1 # overflow $end
$var wire 1 $ cout $end
$var reg 8 % a [7:0] $end
$var reg 8 & a_signed [7:0] $end
$var reg 8 ' b [7:0] $end
$var reg 8 ( b_signed [7:0] $end
$var reg 1 ) cin $end
$scope module uut $end
$var wire 8 * a [7:0] $end
$var wire 8 + b [7:0] $end
$var wire 1 ) cin $end
$var wire 1 # overflow $end
$var wire 8 , sum [7:0] $end
$var wire 1 $ cout $end
$var wire 9 - carry [8:0] $end
$scope begin full_adder_loop[0] $end
$var parameter 2 . i $end
$scope module fa $end
$var wire 1 / a $end
$var wire 1 0 b $end
$var wire 1 1 cin $end
$var wire 1 2 cout $end
$var wire 1 3 sum1 $end
$var wire 1 4 sum $end
$var wire 1 5 carry2 $end
$var wire 1 6 carry1 $end
$scope module ha1 $end
$var wire 1 / a $end
$var wire 1 0 b $end
$var wire 1 6 carry $end
$var wire 1 3 sum $end
$upscope $end
$scope module ha2 $end
$var wire 1 3 a $end
$var wire 1 1 b $end
$var wire 1 5 carry $end
$var wire 1 4 sum $end
$upscope $end
$upscope $end
$upscope $end
$scope begin full_adder_loop[1] $end
$var parameter 2 7 i $end
$scope module fa $end
$var wire 1 8 a $end
$var wire 1 9 b $end
$var wire 1 : cin $end
$var wire 1 ; cout $end
$var wire 1 < sum1 $end
$var wire 1 = sum $end
$var wire 1 > carry2 $end
$var wire 1 ? carry1 $end
$scope module ha1 $end
$var wire 1 8 a $end
$var wire 1 9 b $end
$var wire 1 ? carry $end
$var wire 1 < sum $end
$upscope $end
$scope module ha2 $end
$var wire 1 < a $end
$var wire 1 : b $end
$var wire 1 > carry $end
$var wire 1 = sum $end
$upscope $end
$upscope $end
$upscope $end
$scope begin full_adder_loop[2] $end
$var parameter 3 @ i $end
$scope module fa $end
$var wire 1 A a $end
$var wire 1 B b $end
$var wire 1 C cin $end
$var wire 1 D cout $end
$var wire 1 E sum1 $end
$var wire 1 F sum $end
$var wire 1 G carry2 $end
$var wire 1 H carry1 $end
$scope module ha1 $end
$var wire 1 A a $end
$var wire 1 B b $end
$var wire 1 H carry $end
$var wire 1 E sum $end
$upscope $end
$scope module ha2 $end
$var wire 1 E a $end
$var wire 1 C b $end
$var wire 1 G carry $end
$var wire 1 F sum $end
$upscope $end
$upscope $end
$upscope $end
$scope begin full_adder_loop[3] $end
$var parameter 3 I i $end
$scope module fa $end
$var wire 1 J a $end
$var wire 1 K b $end
$var wire 1 L cin $end
$var wire 1 M cout $end
$var wire 1 N sum1 $end
$var wire 1 O sum $end
$var wire 1 P carry2 $end
$var wire 1 Q carry1 $end
$scope module ha1 $end
$var wire 1 J a $end
$var wire 1 K b $end
$var wire 1 Q carry $end
$var wire 1 N sum $end
$upscope $end
$scope module ha2 $end
$var wire 1 N a $end
$var wire 1 L b $end
$var wire 1 P carry $end
$var wire 1 O sum $end
$upscope $end
$upscope $end
$upscope $end
$scope begin full_adder_loop[4] $end
$var parameter 4 R i $end
$scope module fa $end
$var wire 1 S a $end
$var wire 1 T b $end
$var wire 1 U cin $end
$var wire 1 V cout $end
$var wire 1 W sum1 $end
$var wire 1 X sum $end
$var wire 1 Y carry2 $end
$var wire 1 Z carry1 $end
$scope module ha1 $end
$var wire 1 S a $end
$var wire 1 T b $end
$var wire 1 Z carry $end
$var wire 1 W sum $end
$upscope $end
$scope module ha2 $end
$var wire 1 W a $end
$var wire 1 U b $end
$var wire 1 Y carry $end
$var wire 1 X sum $end
$upscope $end
$upscope $end
$upscope $end
$scope begin full_adder_loop[5] $end
$var parameter 4 [ i $end
$scope module fa $end
$var wire 1 \ a $end
$var wire 1 ] b $end
$var wire 1 ^ cin $end
$var wire 1 _ cout $end
$var wire 1 ` sum1 $end
$var wire 1 a sum $end
$var wire 1 b carry2 $end
$var wire 1 c carry1 $end
$scope module ha1 $end
$var wire 1 \ a $end
$var wire 1 ] b $end
$var wire 1 c carry $end
$var wire 1 ` sum $end
$upscope $end
$scope module ha2 $end
$var wire 1 ` a $end
$var wire 1 ^ b $end
$var wire 1 b carry $end
$var wire 1 a sum $end
$upscope $end
$upscope $end
$upscope $end
$scope begin full_adder_loop[6] $end
$var parameter 4 d i $end
$scope module fa $end
$var wire 1 e a $end
$var wire 1 f b $end
$var wire 1 g cin $end
$var wire 1 h cout $end
$var wire 1 i sum1 $end
$var wire 1 j sum $end
$var wire 1 k carry2 $end
$var wire 1 l carry1 $end
$scope module ha1 $end
$var wire 1 e a $end
$var wire 1 f b $end
$var wire 1 l carry $end
$var wire 1 i sum $end
$upscope $end
$scope module ha2 $end
$var wire 1 i a $end
$var wire 1 g b $end
$var wire 1 k carry $end
$var wire 1 j sum $end
$upscope $end
$upscope $end
$upscope $end
$scope begin full_adder_loop[7] $end
$var parameter 4 m i $end
$scope module fa $end
$var wire 1 n a $end
$var wire 1 o b $end
$var wire 1 p cin $end
$var wire 1 q cout $end
$var wire 1 r sum1 $end
$var wire 1 s sum $end
$var wire 1 t carry2 $end
$var wire 1 u carry1 $end
$scope module ha1 $end
$var wire 1 n a $end
$var wire 1 o b $end
$var wire 1 u carry $end
$var wire 1 r sum $end
$upscope $end
$scope module ha2 $end
$var wire 1 r a $end
$var wire 1 p b $end
$var wire 1 t carry $end
$var wire 1 s sum $end
$upscope $end
$upscope $end
$upscope $end
$upscope $end
$upscope $end
$enddefinitions $end
$comment Show the parameter values. $end
$dumpall
b111 m
b110 d
b101 [
b100 R
b11 I
b10 @
b1 7
b0 .
$end
#0
$dumpvars
0u
0t
0s
0r
0q
0p
0o
0n
0l
0k
0j
0i
0h
0g
0f
0e
0c
0b
0a
0`
0_
0^
0]
0\
0Z
0Y
0X
0W
0V
0U
0T
0S
0Q
0P
0O
0N
0M
0L
0K
0J
0H
0G
0F
0E
0D
0C
0B
0A
0?
0>
0=
0<
0;
0:
09
08
06
05
04
03
02
01
00
0/
b0 -
b0 ,
b0 +
b0 *
0)
b0 (
b0 '
b0 &
b0 %
0$
0#
b0 "
b0 !
$end
#10
b1111 !
b1111 "
b1111 ,
1=
1O
14
1F
1<
1N
13
1E
19
1K
1/
1A
b1010 (
b101 &
b1010 '
b1010 +
b101 %
b101 *
#20
1X
1U
1M
0O
1P
1L
1D
0F
1G
1C
1;
0=
1>
1:
b10000 !
b10000 "
b10000 ,
12
04
15
11
b11111 -
1)
#30
0U
0#
0M
1O
0P
0L
0s
0p
0D
1F
0G
0h
0C
0k
0g
0;
1=
0>
0_
0:
0b
0^
02
b1111111 !
b1111111 "
b1111111 ,
14
05
0V
01
1j
1X
0Y
1a
b0 -
1i
1W
1`
09
0K
1f
18
1J
1S
1\
b1000000 (
b111111 &
0)
b1000000 '
b1000000 +
b111111 %
b111111 *
#40
1#
1s
1p
1h
0j
1k
1g
1_
0a
1b
1^
1V
0X
1Y
1U
1M
0O
1P
1L
1D
0F
1G
1C
1;
0=
1>
1:
b10000000 !
b10000000 "
b10000000 ,
b11111110 -
04
12
03
16
10
0f
1e
b1 (
b1111111 &
b1 '
b1 +
b1111111 %
b1111111 *
#50
0s
0p
0g
0^
0U
1$
0L
0C
0:
b0 !
b0 "
b0 ,
b100000000 -
0;
0D
0M
0V
0_
0h
02
0=
0>
0F
0G
0O
0P
0X
0Y
0a
0b
0j
0k
1q
1#
06
0<
0E
0N
0W
0`
0i
1u
00
1o
0/
08
0A
0J
0S
0\
0e
1n
b10000000 (
b10000000 &
b10000000 '
b10000000 +
b10000000 %
b10000000 *
#60
1t
1p
1h
1k
1g
1_
1b
1^
1V
1Y
1U
1M
1P
1L
1D
1G
1C
1;
1>
1$
1:
b111111110 -
b0 !
b0 "
b0 ,
0s
1q
0#
12
0=
0F
0O
0X
0a
0j
1r
0u
16
1<
1E
1N
1W
1`
1i
10
0o
1/
18
1A
1J
1S
1\
1e
b1 (
b11111111 &
b1 '
b1 +
b11111111 %
b11111111 *
#70
0:
b111111100 -
b1 !
b1 "
b1 ,
14
02
0=
0>
13
06
0<
1?
00
19
b10 (
b10 '
b10 +
#80
0C
b111111000 -
b11111011 !
b11111011 "
b11111011 ,
1=
0;
0F
0G
1O
0P
1X
0Y
1a
0b
1j
0k
1s
0t
0#
1<
0?
0E
1H
0N
1Q
0W
1Z
0`
1c
0i
1l
0r
1u
10
09
1B
1K
1T
1]
1f
1o
0/
b11111101 (
b11111110 &
b11111101 '
b11111101 +
b11111110 %
b11111110 *
#90
1G
1C
1;
0=
1>
1$
1p
1g
1^
1U
1L
1:
b0 !
b0 "
b0 ,
b111111110 -
0F
1D
0O
1P
1M
0X
1Y
1V
0a
1b
1_
0j
1k
1h
0s
1t
1q
04
12
1E
0H
1N
0Q
1W
0Z
1`
0c
1i
0l
1r
0u
03
16
0B
0K
0T
0]
0f
0o
1/
b1 (
b11111111 &
b1 '
b1 +
b11111111 %
b11111111 *
#100
b11111110 !
b11111110 "
b11111110 ,
1=
0>
1F
0G
1O
0P
1X
0Y
1a
0b
1j
0k
1s
0t
0#
0<
1?
0E
1H
0N
1Q
0W
1Z
0`
1c
0i
1l
0r
1u
19
1B
1K
1T
1]
1f
1o
b11111111 (
b11111111 '
b11111111 +
