Full_Adder/Full_Adder_4bit/half_adder.v
module half_adder(
    input a,
    input b,
    output sum,
    output carry
);
    
    // Logic for sum (XOR operation)
    assign sum = a ^ b;
    
    // Logic for carry (AND operation)
    assign carry = a & b;
    
endmodule

Full_Adder/Full_Adder_32bit/full_adder_1bit.v
module full_adder_1bit(
	input a,
	input b,
	input cin,
	output sum,
	output cout
);
	wire sum1;
	wire carry1;
	wire carry2;
	
	half_adder ha1(
               .a(a),
		       .b(b),
		       .sum(sum1),
		       .carry(carry1)
	);
	
	half_adder ha2(
               .a(sum1),
		       .b(cin),
		       .sum(sum),
		       .carry(carry2) 		
	);

	assign cout = carry1 | carry2;
endmodule

Full_Adder/Full_Adder_1bit/full_adder_1bit_tb.v
module full_adder_1bit_tb;
    // Inputs
    reg a;
    reg b;
    reg cin;
    
    // Outputs
    wire sum;
    wire cout;
    
    // Instantiate the Unit Under Test (UUT)
    full_adder_1bit uut (
        .a(a),
        .b(b),
        .cin(cin),
        .sum(sum),
        .cout(cout)
    );
    
    initial begin
        // Initialize inputs
        a = 0; b = 0; cin = 0;
        #10;
        
        a = 0; b = 0; cin = 1;
        #10;
        
        a = 0; b = 1; cin = 0;
        #10;
        
        a = 0; b = 1; cin = 1;
        #10;
        
        a = 1; b = 0; cin = 0;
        #10;
        
        a = 1; b = 0; cin = 1;
        #10;
        
        a = 1; b = 1; cin = 0;
        #10;
        
        a = 1; b = 1; cin = 1;
        #10;
        
        $finish;
    end
    
    // Monitor changes
    initial begin
        $monitor("Time=%0t | a=%b b=%b cin=%b | sum=%b cout=%b", $time, a, b, cin, sum, cout);
        $dumpfile("full_adder_1bit_tb.vcd");
        $dumpvars(0, full_adder_1bit_tb);
    end
endmodule

Full_Adder/Full_Adder_1bit/full_adder_1bit_tb.vcd
$date
	Mon Jun 23 13:22:31 2025
$end
$version
	Icarus Verilog
$end
$timescale
	1s
$end
$scope module full_adder_1bit_tb $end
$var wire 1 ! sum $end
$var wire 1 " cout $end
$var reg 1 # a $end
$var reg 1 $ b $end
$var reg 1 % cin $end
$scope module uut $end
$var wire 1 # a $end
$var wire 1 $ b $end
$var wire 1 % cin $end
$var wire 1 " cout $end
$var wire 1 & sum1 $end
$var wire 1 ! sum $end
$var wire 1 ' carry2 $end
$var wire 1 ( carry1 $end
$scope module ha1 $end
$var wire 1 # a $end
$var wire 1 $ b $end
$var wire 1 ( carry $end
$var wire 1 & sum $end
$upscope $end
$scope module ha2 $end
$var wire 1 & a $end
$var wire 1 % b $end
$var wire 1 ' carry $end
$var wire 1 ! sum $end
$upscope $end
$upscope $end
$upscope $end
$enddefinitions $end
$comment Show the parameter values. $end
$dumpall
$end
#0
$dumpvars
0(
0'
0&
0%
0$
0#
0"
0!
$end
#10
1!
1%
#20
1&
0%
1$
#30
1"
0!
1'
1%
#40
0"
1!
0'
0%
0$
1#
#50
1"
0!
1'
1%
#60
0'
0&
1(
0%
1$
#70
1!
1%
