1_bit_fulladder/half_adder.v
module half_adder (
    input a,
    input b,
    output sum,
    output carry
);
    
    // Half adder logic
    // sum = a XOR b
    // carry = a AND b
    assign sum = a ^ b;
    assign carry = a & b;
    
endmodule

1_bit_fulladder/full_adder.v

module full_adder (
    input a,
    input b,
    input cin,
    output sum,
    output cout
);
    
    // Internal wires
    wire sum1;
    wire carry1;
    wire carry2;
    
    // Instantiate two half adders
    half_adder ha1 (
        .a(a),
        .b(b),
        .sum(sum1),
        .carry(carry1)
    );
    
    half_adder ha2 (
        .a(sum1),
        .b(cin),
        .sum(sum),
        .carry(carry2)
    );
    
    // Final carry out is OR of the two carries
    assign cout = carry1 | carry2;
    
endmodule

1_bit_fulladder/full_adder_tb.v
module full_adder_tb;
    // Testbench signals
    reg a;
    reg b;
    reg cin;
    wire sum;
    wire cout;
    
    // Instantiate the module under test
    full_adder dut (
        .a(a),
        .b(b),
        .cin(cin),
        .sum(sum),
        .cout(cout)
    );
    
    // Test stimulus
    initial begin
        // Test all possible input combinations
        
        // Test case 1: a=0, b=0, cin=0
        a = 0; b = 0; cin = 0;
        #10;
        $display("Test case 1: a = %b, b = %b, cin = %b, sum = %b, cout = %b", a, b, cin, sum, cout);
        
        // Test case 2: a=0, b=0, cin=1
        a = 0; b = 0; cin = 1;
        #10;
        $display("Test case 2: a = %b, b = %b, cin = %b, sum = %b, cout = %b", a, b, cin, sum, cout);
        
        // Test case 3: a=0, b=1, cin=0
        a = 0; b = 1; cin = 0;
        #10;
        $display("Test case 3: a = %b, b = %b, cin = %b, sum = %b, cout = %b", a, b, cin, sum, cout);
        
        // Test case 4: a=0, b=1, cin=1
        a = 0; b = 1; cin = 1;
        #10;
        $display("Test case 4: a = %b, b = %b, cin = %b, sum = %b, cout = %b", a, b, cin, sum, cout);
        
        // Test case 5: a=1, b=0, cin=0
        a = 1; b = 0; cin = 0;
        #10;
        $display("Test case 5: a = %b, b = %b, cin = %b, sum = %b, cout = %b", a, b, cin, sum, cout);
        
        // Test case 6: a=1, b=0, cin=1
        a = 1; b = 0; cin = 1;
        #10;
        $display("Test case 6: a = %b, b = %b, cin = %b, sum = %b, cout = %b", a, b, cin, sum, cout);
        
        // Test case 7: a=1, b=1, cin=0
        a = 1; b = 1; cin = 0;
        #10;
        $display("Test case 7: a = %b, b = %b, cin = %b, sum = %b, cout = %b", a, b, cin, sum, cout);
        
        // Test case 8: a=1, b=1, cin=1
        a = 1; b = 1; cin = 1;
        #10;
        $display("Test case 8: a = %b, b = %b, cin = %b, sum = %b, cout = %b", a, b, cin, sum, cout);
        
        $finish;
    end
    
    // Optional: Generate VCD file for waveform viewing
    initial begin
        $dumpfile("full_adder_tb.vcd");
        $dumpvars(0, full_adder_tb);
    end
    
endmodule

1_bit_fulladder/full_adder_tb.vcd
$date
	Tue Jun 10 22:57:53 2025
$end
$version
	Icarus Verilog
$end
$timescale
	1s
$end
$scope module full_adder_tb $end
$var wire 1 ! sum $end
$var wire 1 " cout $end
$var reg 1 # a $end
$var reg 1 $ b $end
$var reg 1 % cin $end
$scope module dut $end
$var wire 1 # a $end
$var wire 1 $ b $end
$var wire 1 % cin $end
$var wire 1 " cout $end
$var wire 1 & sum1 $end
$var wire 1 ! sum $end
$var wire 1 ' carry2 $end
$var wire 1 ( carry1 $end
$scope module ha1 $end
$var wire 1 # a $end
$var wire 1 $ b $end
$var wire 1 ( carry $end
$var wire 1 & sum $end
$upscope $end
$scope module ha2 $end
$var wire 1 & a $end
$var wire 1 % b $end
$var wire 1 ' carry $end
$var wire 1 ! sum $end
$upscope $end
$upscope $end
$upscope $end
$enddefinitions $end
$comment Show the parameter values. $end
$dumpall
$end
#0
$dumpvars
0(
0'
0&
0%
0$
0#
0"
0!
$end
#10
1!
1%
#20
1&
0%
1$
#30
1"
0!
1'
1%
#40
0"
1!
0'
0%
0$
1#
#50
1"
0!
1'
1%
#60
0'
0&
1(
0%
1$
#70
1!
1%
