priority_encoder_83/priority_encoder_83.v
module priority_encoder_83 (
    input [7:0] in,     // 8-bit input
    output reg [2:0] out,  // 3-bit output
    output reg valid    // Valid output indicator
);

    // Priority encoder logic
    // Higher index inputs have higher priority
    // If no input is active (all 0s), valid = 0
    always @(*) begin
        valid = 1'b1;  // Default: output is valid
        
        if (in[7] == 1'b1) begin
            out = 3'b111;  // Priority 7
        end
        else if (in[6] == 1'b1) begin
            out = 3'b110;  // Priority 6
        end
        else if (in[5] == 1'b1) begin
            out = 3'b101;  // Priority 5
        end
        else if (in[4] == 1'b1) begin
            out = 3'b100;  // Priority 4
        end
        else if (in[3] == 1'b1) begin
            out = 3'b011;  // Priority 3
        end
        else if (in[2] == 1'b1) begin
            out = 3'b010;  // Priority 2
        end
        else if (in[1] == 1'b1) begin
            out = 3'b001;  // Priority 1
        end
        else if (in[0] == 1'b1) begin
            out = 3'b000;  // Priority 0
        end
        else begin
            out = 3'b000;  // Default output
            valid = 1'b0;  // No input is active, output is invalid
        end
    end
    
endmodule

priority_encoder_83/priority_encoder_83_tb.v
module priority_encoder_83_tb;
    // Testbench signals
    reg [7:0] in;
    wire [2:0] out;
    wire valid;
    
    // Instantiate the module under test
    priority_encoder_83 dut (
        .in(in),
        .out(out),
        .valid(valid)
    );
    
    // Test stimulus
    initial begin
        // Test case 1: No input active
        in = 8'b00000000;
        #10;
        $display("Test case 1: in = %b, out = %b, valid = %b", in, out, valid);
        
        // Test case 2: Only in[0] active
        in = 8'b00000001;
        #10;
        $display("Test case 2: in = %b, out = %b, valid = %b", in, out, valid);
        
        // Test case 3: Only in[1] active
        in = 8'b00000010;
        #10;
        $display("Test case 3: in = %b, out = %b, valid = %b", in, out, valid);
        
        // Test case 4: Only in[2] active
        in = 8'b00000100;
        #10;
        $display("Test case 4: in = %b, out = %b, valid = %b", in, out, valid);
        
        // Test case 5: Only in[3] active
        in = 8'b00001000;
        #10;
        $display("Test case 5: in = %b, out = %b, valid = %b", in, out, valid);
        
        // Test case 6: Only in[4] active
        in = 8'b00010000;
        #10;
        $display("Test case 6: in = %b, out = %b, valid = %b", in, out, valid);
        
        // Test case 7: Only in[5] active
        in = 8'b00100000;
        #10;
        $display("Test case 7: in = %b, out = %b, valid = %b", in, out, valid);
        
        // Test case 8: Only in[6] active
        in = 8'b01000000;
        #10;
        $display("Test case 8: in = %b, out = %b, valid = %b", in, out, valid);
        
        // Test case 9: Only in[7] active
        in = 8'b10000000;
        #10;
        $display("Test case 9: in = %b, out = %b, valid = %b", in, out, valid);
        
        // Test case 10: Multiple bits active, in[7] has highest priority
        in = 8'b10101010;
        #10;
        $display("Test case 10: in = %b, out = %b, valid = %b", in, out, valid);
        
        // Test case 11: Multiple bits active, in[6] has highest priority
        in = 8'b01010101;
        #10;
        $display("Test case 11: in = %b, out = %b, valid = %b", in, out, valid);
        
        // Test case 12: Multiple bits active, in[5] has highest priority
        in = 8'b00111100;
        #10;
        $display("Test case 12: in = %b, out = %b, valid = %b", in, out, valid);
        
        // Test case 13: Multiple bits active, in[3] has highest priority
        in = 8'b00001111;
        #10;
        $display("Test case 13: in = %b, out = %b, valid = %b", in, out, valid);
        
        // Test case 14: All inputs active, in[7] has highest priority
        in = 8'b11111111;
        #10;
        $display("Test case 14: in = %b, out = %b, valid = %b", in, out, valid);
        
        $finish;
    end
    
    // Optional: Generate VCD file for waveform viewing
    initial begin
        $dumpfile("priority_encoder_83_tb.vcd");
        $dumpvars(0, priority_encoder_83_tb);
    end
    
endmodule

priority_encoder_83/priority_encoder_83_tb.vcd
$date
	Tue Jun 10 22:36:56 2025
$end
$version
	Icarus Verilog
$end
$timescale
	1s
$end
$scope module priority_encoder_83_tb $end
$var wire 1 ! valid $end
$var wire 3 " out [2:0] $end
$var reg 8 # in [7:0] $end
$scope module dut $end
$var wire 8 $ in [7:0] $end
$var reg 3 % out [2:0] $end
$var reg 1 ! valid $end
$upscope $end
$upscope $end
$enddefinitions $end
$comment Show the parameter values. $end
$dumpall
$end
#0
$dumpvars
b0 %
b0 $
b0 #
b0 "
0!
$end
#10
1!
b1 #
b1 $
#20
b1 "
b1 %
b10 #
b10 $
#30
b10 "
b10 %
b100 #
b100 $
#40
b11 "
b11 %
b1000 #
b1000 $
#50
b100 "
b100 %
b10000 #
b10000 $
#60
b101 "
b101 %
b100000 #
b100000 $
#70
b110 "
b110 %
b1000000 #
b1000000 $
#80
b111 "
b111 %
b10000000 #
b10000000 $
#90
b10101010 #
b10101010 $
#100
b110 "
b110 %
b1010101 #
b1010101 $
#110
b101 "
b101 %
b111100 #
b111100 $
#120
b11 "
b11 %
b1111 #
b1111 $
#130
b111 "
b111 %
b11111111 #
b11111111 $
