priority_encoder_42/priority_encoder_42.v
module priority_encoder_42 (
    input [3:0] in,     // 4-bit input
    output reg [1:0] out,  // 2-bit output
    output reg valid    // Valid output indicator
);

    // Priority encoder logic
    // Higher index inputs have higher priority
    // If no input is active (all 0s), valid = 0
    always @(*) begin
        valid = 1'b1;  // Default: output is valid
        
        if (in[3] == 1'b1) begin
            out = 2'b11;  // Priority 3
        end
        else if (in[2] == 1'b1) begin
            out = 2'b10;  // Priority 2
        end
        else if (in[1] == 1'b1) begin
            out = 2'b01;  // Priority 1
        end
        else if (in[0] == 1'b1) begin
            out = 2'b00;  // Priority 0
        end
        else begin
            out = 2'b00;  // Default output
            valid = 1'b0; // No input is active, output is invalid
        end
    end
    
endmodule

priority_encoder_42/priority_encoder_42_tb.v
module priority_encoder_42_tb;
    // Testbench signals
    reg [3:0] in;
    wire [1:0] out;
    wire valid;
    
    // Instantiate the module under test
    priority_encoder_42 dut (
        .in(in),
        .out(out),
        .valid(valid)
    );
    
    // Test stimulus
    initial begin
        // Test case 1: No input active
        in = 4'b0000;
        #10;
        $display("Test case 1: in = %b, out = %b, valid = %b", in, out, valid);
        
        // Test case 2: Only in[0] active
        in = 4'b0001;
        #10;
        $display("Test case 2: in = %b, out = %b, valid = %b", in, out, valid);
        
        // Test case 3: Only in[1] active
        in = 4'b0010;
        #10;
        $display("Test case 3: in = %b, out = %b, valid = %b", in, out, valid);
        
        // Test case 4: Both in[0] and in[1] active, in[1] has higher priority
        in = 4'b0011;
        #10;
        $display("Test case 4: in = %b, out = %b, valid = %b", in, out, valid);
        
        // Test case 5: Only in[2] active
        in = 4'b0100;
        #10;
        $display("Test case 5: in = %b, out = %b, valid = %b", in, out, valid);
        
        // Test case 6: in[2] and in[0] active, in[2] has higher priority
        in = 4'b0101;
        #10;
        $display("Test case 6: in = %b, out = %b, valid = %b", in, out, valid);
        
        // Test case 7: in[2] and in[1] active, in[2] has higher priority
        in = 4'b0110;
        #10;
        $display("Test case 7: in = %b, out = %b, valid = %b", in, out, valid);
        
        // Test case 8: in[2], in[1], and in[0] active, in[2] has highest priority
        in = 4'b0111;
        #10;
        $display("Test case 8: in = %b, out = %b, valid = %b", in, out, valid);
        
        // Test case 9: Only in[3] active
        in = 4'b1000;
        #10;
        $display("Test case 9: in = %b, out = %b, valid = %b", in, out, valid);
        
        // Test case 10: in[3] and in[0] active, in[3] has higher priority
        in = 4'b1001;
        #10;
        $display("Test case 10: in = %b, out = %b, valid = %b", in, out, valid);
        
        // Test case 11: in[3] and in[1] active, in[3] has higher priority
        in = 4'b1010;
        #10;
        $display("Test case 11: in = %b, out = %b, valid = %b", in, out, valid);
        
        // Test case 12: in[3], in[1], and in[0] active, in[3] has highest priority
        in = 4'b1011;
        #10;
        $display("Test case 12: in = %b, out = %b, valid = %b", in, out, valid);
        
        // Test case 13: in[3] and in[2] active, in[3] has higher priority
        in = 4'b1100;
        #10;
        $display("Test case 13: in = %b, out = %b, valid = %b", in, out, valid);
        
        // Test case 14: in[3], in[2], and in[0] active, in[3] has highest priority
        in = 4'b1101;
        #10;
        $display("Test case 14: in = %b, out = %b, valid = %b", in, out, valid);
        
        // Test case 15: in[3], in[2], and in[1] active, in[3] has highest priority
        in = 4'b1110;
        #10;
        $display("Test case 15: in = %b, out = %b, valid = %b", in, out, valid);
        
        // Test case 16: All inputs active, in[3] has highest priority
        in = 4'b1111;
        #10;
        $display("Test case 16: in = %b, out = %b, valid = %b", in, out, valid);
        
        $finish;
    end
    
    // Optional: Generate VCD file for waveform viewing
    initial begin
        $dumpfile("priority_encoder_42_tb.vcd");
        $dumpvars(0, priority_encoder_42_tb);
    end
    
endmodule

priority_encoder_42/priority_encoder_42_tb.vcd
$date
	Tue Jun 10 22:31:36 2025
$end
$version
	Icarus Verilog
$end
$timescale
	1s
$end
$scope module priority_encoder_42_tb $end
$var wire 1 ! valid $end
$var wire 2 " out [1:0] $end
$var reg 4 # in [3:0] $end
$scope module dut $end
$var wire 4 $ in [3:0] $end
$var reg 2 % out [1:0] $end
$var reg 1 ! valid $end
$upscope $end
$upscope $end
$enddefinitions $end
$comment Show the parameter values. $end
$dumpall
$end
#0
$dumpvars
b0 %
b0 $
b0 #
b0 "
0!
$end
#10
1!
b1 #
b1 $
#20
b1 "
b1 %
b10 #
b10 $
#30
b11 #
b11 $
#40
b10 "
b10 %
b100 #
b100 $
#50
b101 #
b101 $
#60
b110 #
b110 $
#70
b111 #
b111 $
#80
b11 "
b11 %
b1000 #
b1000 $
#90
b1001 #
b1001 $
#100
b1010 #
b1010 $
#110
b1011 #
b1011 $
#120
b1100 #
b1100 $
#130
b1101 #
b1101 $
#140
b1110 #
b1110 $
#150
b1111 #
b1111 $
