4bit_comparator/4bit_comparator.v
module bit4_comparator (
    input [3:0] a,      // 4-bit input a
    input [3:0] b,      // 4-bit input b
    output reg equal,   // Equal output (a == b)
    output reg greater, // Greater output (a > b)
    output reg less     // Less output (a < b)
);

    // Comparator logic
    always @(*) begin
        // Default values
        equal = 1'b0;
        greater = 1'b0;
        less = 1'b0;
        
        // Compare a and b
        if (a == b) begin
            equal = 1'b1;
        end
        else if (a > b) begin
            greater = 1'b1;
        end
        else begin
            less = 1'b1;
        end
    end
    
endmodule

4bit_comparator/4bit_comparator_tb.v
module bit4_comparator_tb;
    // Testbench signals
    reg [3:0] a;
    reg [3:0] b;
    wire equal;
    wire greater;
    wire less;
    
    // Instantiate the module under test
    bit4_comparator dut (
        .a(a),
        .b(b),
        .equal(equal),
        .greater(greater),
        .less(less)
    );
    
    // Test stimulus
    initial begin
        // Test case 1: a = b
        a = 4'b0000; b = 4'b0000;
        #10;
        $display("Test case 1: a = %b, b = %b, equal = %b, greater = %b, less = %b", a, b, equal, greater, less);
        
        // Test case 2: a = b (different value)
        a = 4'b1010; b = 4'b1010;
        #10;
        $display("Test case 2: a = %b, b = %b, equal = %b, greater = %b, less = %b", a, b, equal, greater, less);
        
        // Test case 3: a > b (small difference)
        a = 4'b0101; b = 4'b0100;
        #10;
        $display("Test case 3: a = %b, b = %b, equal = %b, greater = %b, less = %b", a, b, equal, greater, less);
        
        // Test case 4: a > b (large difference)
        a = 4'b1111; b = 4'b0000;
        #10;
        $display("Test case 4: a = %b, b = %b, equal = %b, greater = %b, less = %b", a, b, equal, greater, less);
        
        // Test case 5: a < b (small difference)
        a = 4'b0110; b = 4'b0111;
        #10;
        $display("Test case 5: a = %b, b = %b, equal = %b, greater = %b, less = %b", a, b, equal, greater, less);
        
        // Test case 6: a < b (large difference)
        a = 4'b0001; b = 4'b1111;
        #10;
        $display("Test case 6: a = %b, b = %b, equal = %b, greater = %b, less = %b", a, b, equal, greater, less);
        
        // Test case 7: a > b (MSB difference)
        a = 4'b1000; b = 4'b0111;
        #10;
        $display("Test case 7: a = %b, b = %b, equal = %b, greater = %b, less = %b", a, b, equal, greater, less);
        
        // Test case 8: a < b (MSB difference)
        a = 4'b0111; b = 4'b1000;
        #10;
        $display("Test case 8: a = %b, b = %b, equal = %b, greater = %b, less = %b", a, b, equal, greater, less);
        
        $finish;
    end
    
    // Optional: Generate VCD file for waveform viewing
    initial begin
        $dumpfile("bit4_comparator_tb.vcd");
        $dumpvars(0, bit4_comparator_tb);
    end
    
endmodule

4bit_comparator/bit4_comparator_tb.vcd
$date
	Tue Jun 10 22:46:19 2025
$end
$version
	Icarus Verilog
$end
$timescale
	1s
$end
$scope module bit4_comparator_tb $end
$var wire 1 ! less $end
$var wire 1 " greater $end
$var wire 1 # equal $end
$var reg 4 $ a [3:0] $end
$var reg 4 % b [3:0] $end
$scope module dut $end
$var wire 4 & a [3:0] $end
$var wire 4 ' b [3:0] $end
$var reg 1 # equal $end
$var reg 1 " greater $end
$var reg 1 ! less $end
$upscope $end
$upscope $end
$enddefinitions $end
$comment Show the parameter values. $end
$dumpall
$end
#0
$dumpvars
b0 '
b0 &
b0 %
b0 $
1#
0"
0!
$end
#10
1#
b1010 %
b1010 '
b1010 $
b1010 &
#20
1"
0#
b100 %
b100 '
b101 $
b101 &
#30
1"
b0 %
b0 '
b1111 $
b1111 &
#40
1!
0"
b111 %
b111 '
b110 $
b110 &
#50
1!
b1111 %
b1111 '
b1 $
b1 &
#60
1"
0!
b111 %
b111 '
b1000 $
b1000 &
#70
1!
0"
b1000 %
b1000 '
b111 $
b111 &
