Full_Adder/Full_Adder_4bit/half_adder.v
module half_adder(
    input a,
    input b,
    output sum,
    output carry
);
    
    // Logic for sum (XOR operation)
    assign sum = a ^ b;
    
    // Logic for carry (AND operation)
    assign carry = a & b;
    
endmodule

Full_Adder/Full_Adder_32bit/full_adder_1bit.v
module full_adder_1bit(
	input a,
	input b,
	input cin,
	output sum,
	output cout
);
	wire sum1;
	wire carry1;
	wire carry2;
	
	half_adder ha1(
               .a(a),
		       .b(b),
		       .sum(sum1),
		       .carry(carry1)
	);
	
	half_adder ha2(
               .a(sum1),
		       .b(cin),
		       .sum(sum),
		       .carry(carry2) 		
	);

	assign cout = carry1 | carry2;
endmodule

Full_Adder/Full_Adder_16bit/full_adder_16bit.v
/*module full_adder_16bit(
    input [15:0] a,
    input [15:0] b,
    input cin,
    output [15:0] sum,
    output cout,
    output overflow
);
    wire [16:0] carry;
    assign carry[0] = cin;
    assign cout = carry[16];

    full_adder_1bit fa1(
        .a(a[0]),
        .b(b[0]),
        .cin(carry[0]),
        .sum(sum[0]),
        .cout(carry[1])
    );

    full_adder_1bit fa2(
        .a(a[1]),
        .b(b[1]),
        .cin(carry[1]),
        .sum(sum[1]),
        .cout(carry[2])
    );

    full_adder_1bit fa3(
        .a(a[2]),
        .b(b[2]),
        .cin(carry[2]),
        .sum(sum[2]),
        .cout(carry[3])
    );

    full_adder_1bit fa4(
        .a(a[3]),
        .b(b[3]),
        .cin(carry[3]),
        .sum(sum[3]),
        .cout(carry[4])
    );

    full_adder_1bit fa5(
        .a(a[4]),
        .b(b[4]),
        .cin(carry[4]),
        .sum(sum[4]),
        .cout(carry[5])
    );

    full_adder_1bit fa6(
        .a(a[5]),
        .b(b[5]),
        .cin(carry[5]),
        .sum(sum[5]),
        .cout(carry[6])
    );

    full_adder_1bit fa7(
        .a(a[6]),
        .b(b[6]),
        .cin(carry[6]),
        .sum(sum[6]),
        .cout(carry[7])
    );

    full_adder_1bit fa8(
        .a(a[7]),
        .b(b[7]),
        .cin(carry[7]),
        .sum(sum[7]),
        .cout(carry[8])
    );

    full_adder_1bit fa9(
        .a(a[8]),
        .b(b[8]),
        .cin(carry[8]),
        .sum(sum[8]),
        .cout(carry[9])
    );

    full_adder_1bit fa10(
        .a(a[9]),
        .b(b[9]),
        .cin(carry[9]),
        .sum(sum[9]),
        .cout(carry[10])
    );

    full_adder_1bit fa11(
        .a(a[10]),
        .b(b[10]),
        .cin(carry[10]),
        .sum(sum[10]),
        .cout(carry[11])
    );
    
    full_adder_1bit fa12(
        .a(a[11]),
        .b(b[11]),
        .cin(carry[11]),
        .sum(sum[11]),
        .cout(carry[12])
    );
    
    full_adder_1bit fa13(
        .a(a[12]),
        .b(b[12]),
        .cin(carry[12]),
        .sum(sum[12]),
        .cout(carry[13])
    );
    
    full_adder_1bit fa14(
        .a(a[13]),
        .b(b[13]),
        .cin(carry[13]),
        .sum(sum[13]),
        .cout(carry[14])
    );
    
    full_adder_1bit fa15(
        .a(a[14]),
        .b(b[14]),
        .cin(carry[14]),
        .sum(sum[14]),
        .cout(carry[15])
    );

    full_adder_1bit fa16(
        .a(a[15]),
        .b(b[15]),
        .cin(carry[15]),
        .sum(sum[15]),
        .cout(carry[16])
    );

    assign overflow = (a[15] == b[15]) && (a[15] != sum[15]);
endmodule */

module full_adder_16bit(
    input [15:0] a,
    input [15:0] b,
    input cin,
    output [15:0] sum,
    output cout,
    output overflow
);
    wire [16:0] carry;
    assign carry[0] = cin;
    assign cout = carry[16];

    genvar i;
    generate 
        for (i = 0 ; i < 16 ; i = i + 1) begin : full_adder_loop
            full_adder_1bit fa(
                .a(a[i]),
                .b(b[i]),
                .cin(carry[i]),
                .sum(sum[i]),
                .cout(carry[i+1])
            );
        end
    endgenerate
    assign overflow = (a[15] == b[15]) && (a[15] != sum[15]);
endmodule

Full_Adder/Full_Adder_16bit/full_adder_16bit_tb.v
module full_adder_16bit_tb;
    // Inputs
    reg [15:0] a;
    reg [15:0] b;
    reg cin;
    
    // Outputs
    wire [15:0] sum;
    wire cout;
    wire overflow;
    
    // Biến phụ để hiển thị số có dấu
    reg signed [15:0] a_signed;
    reg signed [15:0] b_signed;
    wire signed [15:0] sum_signed;
    
    // Instantiate the Unit Under Test (UUT)
    full_adder_16bit uut (
        .a(a),
        .b(b),
        .cin(cin),
        .sum(sum),
        .cout(cout),
        .overflow(overflow)
    );
    
    // Gán giá trị cho biến phụ
    always @* begin
        a_signed = a;
        b_signed = b;
    end
    
    assign sum_signed = sum;
    
    initial begin
        // Initialize inputs
        a = 0; b = 0; cin = 0;
        #10;
        
        // Test case 1: Simple addition (không tràn số)
        a = 16'h0005; b = 16'h000A; cin = 0; // 5 + 10 = 15
        #10;
        
        // Test case 2: Addition with carry-in
        a = 16'h0005; b = 16'h000A; cin = 1; // 5 + 10 + 1 = 16
        #10;
        
        // Test case 3: Larger numbers (không tràn số)
        a = 16'h03FF; b = 16'h0400; cin = 0; // 1023 + 1024 = 2047
        #10;
        
        // Test case 4: Overflow dương (hai số dương ra số âm)
        a = 16'h7FFF; b = 16'h0001; cin = 0; // 32767 + 1 = 32768 (overflow, kết quả là -32768)
        #10;
        
        // Test case 5: Overflow âm (hai số âm ra số dương)
        a = 16'h8000; b = 16'h8000; cin = 0; // -32768 + -32768 = -65536 (overflow, kết quả là 0 với cout=1)
        #10;
        
        // Test case 6: Số âm + số dương = số âm (không overflow)
        a = 16'hFFFF; b = 16'h0001; cin = 0; // -1 + 1 = 0
        #10;
        
        // Test case 7: Số âm + số dương = số dương (không overflow)
        a = 16'hFFFF; b = 16'h0002; cin = 0; // -1 + 2 = 1
        #10;
        
        // Test case 8: Số âm + số âm (không overflow)
        a = 16'hFFFE; b = 16'hFFFD; cin = 0; // -2 + -3 = -5
        #10;
        
        // Test case 9: Carry out nhưng không overflow
        a = 16'hFFFF; b = 16'h0001; cin = 0; // 65535 + 1 = 65536 (cout=1, sum=0) hoặc -1 + 1 = 0 (không overflow)
        #10;
        
        // Test case 10: Maximum unsigned value
        a = 16'hFFFF; b = 16'hFFFF; cin = 0; // 65535 + 65535 = 131070 (cout=1, sum=FFFE)
        #10;
        
        $finish;
    end
    
    // Display results with hex và decimal format
    initial begin
        $monitor("Time=%0t | a=%h(%0d/%0d) b=%h(%0d/%0d) cin=%b | sum=%h(%0d/%0d) cout=%b overflow=%b", 
                 $time, a, a, a_signed, b, b, b_signed, cin, sum, sum, sum_signed, cout, overflow);
        $dumpfile("full_adder_16bit_tb.vcd");
        $dumpvars(0, full_adder_16bit_tb);
    end
endmodule

Full_Adder/Full_Adder_16bit/full_adder_16bit_tb.vcd
$date
	Mon Jun 23 20:44:15 2025
$end
$version
	Icarus Verilog
$end
$timescale
	1s
$end
$scope module full_adder_16bit_tb $end
$var wire 16 ! sum_signed [15:0] $end
$var wire 16 " sum [15:0] $end
$var wire 1 # overflow $end
$var wire 1 $ cout $end
$var reg 16 % a [15:0] $end
$var reg 16 & a_signed [15:0] $end
$var reg 16 ' b [15:0] $end
$var reg 16 ( b_signed [15:0] $end
$var reg 1 ) cin $end
$scope module uut $end
$var wire 16 * a [15:0] $end
$var wire 16 + b [15:0] $end
$var wire 1 ) cin $end
$var wire 1 # overflow $end
$var wire 16 , sum [15:0] $end
$var wire 1 $ cout $end
$var wire 17 - carry [16:0] $end
$scope begin full_adder_loop[0] $end
$var parameter 2 . i $end
$scope module fa $end
$var wire 1 / a $end
$var wire 1 0 b $end
$var wire 1 1 cin $end
$var wire 1 2 cout $end
$var wire 1 3 sum1 $end
$var wire 1 4 sum $end
$var wire 1 5 carry2 $end
$var wire 1 6 carry1 $end
$scope module ha1 $end
$var wire 1 / a $end
$var wire 1 0 b $end
$var wire 1 6 carry $end
$var wire 1 3 sum $end
$upscope $end
$scope module ha2 $end
$var wire 1 3 a $end
$var wire 1 1 b $end
$var wire 1 5 carry $end
$var wire 1 4 sum $end
$upscope $end
$upscope $end
$upscope $end
$scope begin full_adder_loop[1] $end
$var parameter 2 7 i $end
$scope module fa $end
$var wire 1 8 a $end
$var wire 1 9 b $end
$var wire 1 : cin $end
$var wire 1 ; cout $end
$var wire 1 < sum1 $end
$var wire 1 = sum $end
$var wire 1 > carry2 $end
$var wire 1 ? carry1 $end
$scope module ha1 $end
$var wire 1 8 a $end
$var wire 1 9 b $end
$var wire 1 ? carry $end
$var wire 1 < sum $end
$upscope $end
$scope module ha2 $end
$var wire 1 < a $end
$var wire 1 : b $end
$var wire 1 > carry $end
$var wire 1 = sum $end
$upscope $end
$upscope $end
$upscope $end
$scope begin full_adder_loop[2] $end
$var parameter 3 @ i $end
$scope module fa $end
$var wire 1 A a $end
$var wire 1 B b $end
$var wire 1 C cin $end
$var wire 1 D cout $end
$var wire 1 E sum1 $end
$var wire 1 F sum $end
$var wire 1 G carry2 $end
$var wire 1 H carry1 $end
$scope module ha1 $end
$var wire 1 A a $end
$var wire 1 B b $end
$var wire 1 H carry $end
$var wire 1 E sum $end
$upscope $end
$scope module ha2 $end
$var wire 1 E a $end
$var wire 1 C b $end
$var wire 1 G carry $end
$var wire 1 F sum $end
$upscope $end
$upscope $end
$upscope $end
$scope begin full_adder_loop[3] $end
$var parameter 3 I i $end
$scope module fa $end
$var wire 1 J a $end
$var wire 1 K b $end
$var wire 1 L cin $end
$var wire 1 M cout $end
$var wire 1 N sum1 $end
$var wire 1 O sum $end
$var wire 1 P carry2 $end
$var wire 1 Q carry1 $end
$scope module ha1 $end
$var wire 1 J a $end
$var wire 1 K b $end
$var wire 1 Q carry $end
$var wire 1 N sum $end
$upscope $end
$scope module ha2 $end
$var wire 1 N a $end
$var wire 1 L b $end
$var wire 1 P carry $end
$var wire 1 O sum $end
$upscope $end
$upscope $end
$upscope $end
$scope begin full_adder_loop[4] $end
$var parameter 4 R i $end
$scope module fa $end
$var wire 1 S a $end
$var wire 1 T b $end
$var wire 1 U cin $end
$var wire 1 V cout $end
$var wire 1 W sum1 $end
$var wire 1 X sum $end
$var wire 1 Y carry2 $end
$var wire 1 Z carry1 $end
$scope module ha1 $end
$var wire 1 S a $end
$var wire 1 T b $end
$var wire 1 Z carry $end
$var wire 1 W sum $end
$upscope $end
$scope module ha2 $end
$var wire 1 W a $end
$var wire 1 U b $end
$var wire 1 Y carry $end
$var wire 1 X sum $end
$upscope $end
$upscope $end
$upscope $end
$scope begin full_adder_loop[5] $end
$var parameter 4 [ i $end
$scope module fa $end
$var wire 1 \ a $end
$var wire 1 ] b $end
$var wire 1 ^ cin $end
$var wire 1 _ cout $end
$var wire 1 ` sum1 $end
$var wire 1 a sum $end
$var wire 1 b carry2 $end
$var wire 1 c carry1 $end
$scope module ha1 $end
$var wire 1 \ a $end
$var wire 1 ] b $end
$var wire 1 c carry $end
$var wire 1 ` sum $end
$upscope $end
$scope module ha2 $end
$var wire 1 ` a $end
$var wire 1 ^ b $end
$var wire 1 b carry $end
$var wire 1 a sum $end
$upscope $end
$upscope $end
$upscope $end
$scope begin full_adder_loop[6] $end
$var parameter 4 d i $end
$scope module fa $end
$var wire 1 e a $end
$var wire 1 f b $end
$var wire 1 g cin $end
$var wire 1 h cout $end
$var wire 1 i sum1 $end
$var wire 1 j sum $end
$var wire 1 k carry2 $end
$var wire 1 l carry1 $end
$scope module ha1 $end
$var wire 1 e a $end
$var wire 1 f b $end
$var wire 1 l carry $end
$var wire 1 i sum $end
$upscope $end
$scope module ha2 $end
$var wire 1 i a $end
$var wire 1 g b $end
$var wire 1 k carry $end
$var wire 1 j sum $end
$upscope $end
$upscope $end
$upscope $end
$scope begin full_adder_loop[7] $end
$var parameter 4 m i $end
$scope module fa $end
$var wire 1 n a $end
$var wire 1 o b $end
$var wire 1 p cin $end
$var wire 1 q cout $end
$var wire 1 r sum1 $end
$var wire 1 s sum $end
$var wire 1 t carry2 $end
$var wire 1 u carry1 $end
$scope module ha1 $end
$var wire 1 n a $end
$var wire 1 o b $end
$var wire 1 u carry $end
$var wire 1 r sum $end
$upscope $end
$scope module ha2 $end
$var wire 1 r a $end
$var wire 1 p b $end
$var wire 1 t carry $end
$var wire 1 s sum $end
$upscope $end
$upscope $end
$upscope $end
$scope begin full_adder_loop[8] $end
$var parameter 5 v i $end
$scope module fa $end
$var wire 1 w a $end
$var wire 1 x b $end
$var wire 1 y cin $end
$var wire 1 z cout $end
$var wire 1 { sum1 $end
$var wire 1 | sum $end
$var wire 1 } carry2 $end
$var wire 1 ~ carry1 $end
$scope module ha1 $end
$var wire 1 w a $end
$var wire 1 x b $end
$var wire 1 ~ carry $end
$var wire 1 { sum $end
$upscope $end
$scope module ha2 $end
$var wire 1 { a $end
$var wire 1 y b $end
$var wire 1 } carry $end
$var wire 1 | sum $end
$upscope $end
$upscope $end
$upscope $end
$scope begin full_adder_loop[9] $end
$var parameter 5 !" i $end
$scope module fa $end
$var wire 1 "" a $end
$var wire 1 #" b $end
$var wire 1 $" cin $end
$var wire 1 %" cout $end
$var wire 1 &" sum1 $end
$var wire 1 '" sum $end
$var wire 1 (" carry2 $end
$var wire 1 )" carry1 $end
$scope module ha1 $end
$var wire 1 "" a $end
$var wire 1 #" b $end
$var wire 1 )" carry $end
$var wire 1 &" sum $end
$upscope $end
$scope module ha2 $end
$var wire 1 &" a $end
$var wire 1 $" b $end
$var wire 1 (" carry $end
$var wire 1 '" sum $end
$upscope $end
$upscope $end
$upscope $end
$scope begin full_adder_loop[10] $end
$var parameter 5 *" i $end
$scope module fa $end
$var wire 1 +" a $end
$var wire 1 ," b $end
$var wire 1 -" cin $end
$var wire 1 ." cout $end
$var wire 1 /" sum1 $end
$var wire 1 0" sum $end
$var wire 1 1" carry2 $end
$var wire 1 2" carry1 $end
$scope module ha1 $end
$var wire 1 +" a $end
$var wire 1 ," b $end
$var wire 1 2" carry $end
$var wire 1 /" sum $end
$upscope $end
$scope module ha2 $end
$var wire 1 /" a $end
$var wire 1 -" b $end
$var wire 1 1" carry $end
$var wire 1 0" sum $end
$upscope $end
$upscope $end
$upscope $end
$scope begin full_adder_loop[11] $end
$var parameter 5 3" i $end
$scope module fa $end
$var wire 1 4" a $end
$var wire 1 5" b $end
$var wire 1 6" cin $end
$var wire 1 7" cout $end
$var wire 1 8" sum1 $end
$var wire 1 9" sum $end
$var wire 1 :" carry2 $end
$var wire 1 ;" carry1 $end
$scope module ha1 $end
$var wire 1 4" a $end
$var wire 1 5" b $end
$var wire 1 ;" carry $end
$var wire 1 8" sum $end
$upscope $end
$scope module ha2 $end
$var wire 1 8" a $end
$var wire 1 6" b $end
$var wire 1 :" carry $end
$var wire 1 9" sum $end
$upscope $end
$upscope $end
$upscope $end
$scope begin full_adder_loop[12] $end
$var parameter 5 <" i $end
$scope module fa $end
$var wire 1 =" a $end
$var wire 1 >" b $end
$var wire 1 ?" cin $end
$var wire 1 @" cout $end
$var wire 1 A" sum1 $end
$var wire 1 B" sum $end
$var wire 1 C" carry2 $end
$var wire 1 D" carry1 $end
$scope module ha1 $end
$var wire 1 =" a $end
$var wire 1 >" b $end
$var wire 1 D" carry $end
$var wire 1 A" sum $end
$upscope $end
$scope module ha2 $end
$var wire 1 A" a $end
$var wire 1 ?" b $end
$var wire 1 C" carry $end
$var wire 1 B" sum $end
$upscope $end
$upscope $end
$upscope $end
$scope begin full_adder_loop[13] $end
$var parameter 5 E" i $end
$scope module fa $end
$var wire 1 F" a $end
$var wire 1 G" b $end
$var wire 1 H" cin $end
$var wire 1 I" cout $end
$var wire 1 J" sum1 $end
$var wire 1 K" sum $end
$var wire 1 L" carry2 $end
$var wire 1 M" carry1 $end
$scope module ha1 $end
$var wire 1 F" a $end
$var wire 1 G" b $end
$var wire 1 M" carry $end
$var wire 1 J" sum $end
$upscope $end
$scope module ha2 $end
$var wire 1 J" a $end
$var wire 1 H" b $end
$var wire 1 L" carry $end
$var wire 1 K" sum $end
$upscope $end
$upscope $end
$upscope $end
$scope begin full_adder_loop[14] $end
$var parameter 5 N" i $end
$scope module fa $end
$var wire 1 O" a $end
$var wire 1 P" b $end
$var wire 1 Q" cin $end
$var wire 1 R" cout $end
$var wire 1 S" sum1 $end
$var wire 1 T" sum $end
$var wire 1 U" carry2 $end
$var wire 1 V" carry1 $end
$scope module ha1 $end
$var wire 1 O" a $end
$var wire 1 P" b $end
$var wire 1 V" carry $end
$var wire 1 S" sum $end
$upscope $end
$scope module ha2 $end
$var wire 1 S" a $end
$var wire 1 Q" b $end
$var wire 1 U" carry $end
$var wire 1 T" sum $end
$upscope $end
$upscope $end
$upscope $end
$scope begin full_adder_loop[15] $end
$var parameter 5 W" i $end
$scope module fa $end
$var wire 1 X" a $end
$var wire 1 Y" b $end
$var wire 1 Z" cin $end
$var wire 1 [" cout $end
$var wire 1 \" sum1 $end
$var wire 1 ]" sum $end
$var wire 1 ^" carry2 $end
$var wire 1 _" carry1 $end
$scope module ha1 $end
$var wire 1 X" a $end
$var wire 1 Y" b $end
$var wire 1 _" carry $end
$var wire 1 \" sum $end
$upscope $end
$scope module ha2 $end
$var wire 1 \" a $end
$var wire 1 Z" b $end
$var wire 1 ^" carry $end
$var wire 1 ]" sum $end
$upscope $end
$upscope $end
$upscope $end
$upscope $end
$upscope $end
$enddefinitions $end
$comment Show the parameter values. $end
$dumpall
b1111 W"
b1110 N"
b1101 E"
b1100 <"
b1011 3"
b1010 *"
b1001 !"
b1000 v
b111 m
b110 d
b101 [
b100 R
b11 I
b10 @
b1 7
b0 .
$end
#0
$dumpvars
0_"
0^"
0]"
0\"
0["
0Z"
0Y"
0X"
0V"
0U"
0T"
0S"
0R"
0Q"
0P"
0O"
0M"
0L"
0K"
0J"
0I"
0H"
0G"
0F"
0D"
0C"
0B"
0A"
0@"
0?"
0>"
0="
0;"
0:"
09"
08"
07"
06"
05"
04"
02"
01"
00"
0/"
0."
0-"
0,"
0+"
0)"
0("
0'"
0&"
0%"
0$"
0#"
0""
0~
0}
0|
0{
0z
0y
0x
0w
0u
0t
0s
0r
0q
0p
0o
0n
0l
0k
0j
0i
0h
0g
0f
0e
0c
0b
0a
0`
0_
0^
0]
0\
0Z
0Y
0X
0W
0V
0U
0T
0S
0Q
0P
0O
0N
0M
0L
0K
0J
0H
0G
0F
0E
0D
0C
0B
0A
0?
0>
0=
0<
0;
0:
09
08
06
05
04
03
02
01
00
0/
b0 -
b0 ,
b0 +
b0 *
0)
b0 (
b0 '
b0 &
b0 %
0$
0#
b0 "
b0 !
$end
#10
b1111 !
b1111 "
b1111 ,
1=
1O
14
1F
1<
1N
13
1E
19
1K
1/
1A
b1010 (
b101 &
b1010 '
b1010 +
b101 %
b101 *
#20
1X
1U
1M
0O
1P
1L
1D
0F
1G
1C
1;
0=
1>
1:
b10000 !
b10000 "
b10000 ,
12
04
15
11
b11111 -
1)
#30
09"
06"
0."
01"
0-"
0%"
0("
0$"
0U
0z
0}
0y
0M
1O
0P
0L
0q
0t
0p
0D
1F
0G
0C
0h
0k
0g
0;
1=
0>
0:
0_
0b
0^
02
14
05
b11111111111 !
b11111111111 "
b11111111111 ,
01
0V
b0 -
10"
1X
0Y
1a
1j
1s
1|
1'"
1/"
1W
1`
1i
1r
1{
1&"
09
0K
1,"
18
1J
1S
1\
1e
1n
1w
1""
b10000000000 (
b1111111111 &
0)
b10000000000 '
b10000000000 +
b1111111111 %
b1111111111 *
#40
1#
1]"
1Z"
1R"
1U"
1Q"
1I"
1L"
1H"
1@"
1C"
1?"
17"
1:"
16"
1."
00"
11"
1-"
1%"
0'"
1("
1$"
1z
0|
1}
1y
1q
0s
1t
1p
1h
0j
1k
1g
1_
0a
1b
1^
1V
0X
1Y
1U
1M
0O
1P
1L
1D
0F
1G
1C
1;
0=
1>
1:
b1111111111111110 -
b1000000000000000 !
b1000000000000000 "
b1000000000000000 ,
04
12
09"
0B"
0K"
0T"
03
16
18"
1A"
1J"
1S"
10
0,"
1+"
14"
1="
1F"
1O"
b1 (
b111111111111111 &
b1 '
b1 +
b111111111111111 %
b111111111111111 *
#50
0]"
1$
0Z"
0Q"
0H"
0?"
06"
0-"
0$"
0y
0p
0g
0^
0U
0L
0C
0:
b10000000000000000 -
b0 !
b0 "
b0 ,
0;
0D
0M
0V
0_
0h
0q
0z
0%"
0."
07"
0@"
0I"
0R"
02
0=
0>
0F
0G
0O
0P
0X
0Y
0a
0b
0j
0k
0s
0t
0|
0}
0'"
0("
00"
01"
09"
0:"
0B"
0C"
0K"
0L"
0T"
0U"
1["
1#
06
0<
0E
0N
0W
0`
0i
0r
0{
0&"
0/"
08"
0A"
0J"
0S"
1_"
00
1Y"
0/
08
0A
0J
0S
0\
0e
0n
0w
0""
0+"
04"
0="
0F"
0O"
1X"
b1000000000000000 (
b1000000000000000 &
b1000000000000000 '
b1000000000000000 +
b1000000000000000 %
b1000000000000000 *
#60
1^"
1Z"
1R"
1U"
1Q"
1I"
1L"
1H"
1@"
1C"
1?"
17"
1:"
16"
1."
11"
1-"
1%"
1("
1$"
1z
1}
1y
1q
1t
1p
1h
1k
1g
1_
1b
1^
1V
1Y
1U
1M
1P
1L
1D
1G
1C
1;
1>
1$
1:
b11111111111111110 -
b0 !
b0 "
b0 ,
0]"
1["
0#
12
0=
0F
0O
0X
0a
0j
0s
0|
0'"
00"
09"
0B"
0K"
0T"
1\"
0_"
16
1<
1E
1N
1W
1`
1i
1r
1{
1&"
1/"
18"
1A"
1J"
1S"
10
0Y"
1/
18
1A
1J
1S
1\
1e
1n
1w
1""
1+"
14"
1="
1F"
1O"
b1 (
b1111111111111111 &
b1 '
b1 +
b1111111111111111 %
b1111111111111111 *
#70
0:
b11111111111111100 -
b1 !
b1 "
b1 ,
14
02
0=
0>
13
06
0<
1?
00
19
b10 (
b10 '
b10 +
#80
0C
b11111111111111000 -
b1111111111111011 !
b1111111111111011 "
b1111111111111011 ,
1=
0;
0F
0G
1O
0P
1X
0Y
1a
0b
1j
0k
1s
0t
1|
0}
1'"
0("
10"
01"
19"
0:"
1B"
0C"
1K"
0L"
1T"
0U"
1]"
0^"
0#
1<
0?
0E
1H
0N
1Q
0W
1Z
0`
1c
0i
1l
0r
1u
0{
1~
0&"
1)"
0/"
12"
08"
1;"
0A"
1D"
0J"
1M"
0S"
1V"
0\"
1_"
10
09
1B
1K
1T
1]
1f
1o
1x
1#"
1,"
15"
1>"
1G"
1P"
1Y"
0/
b1111111111111101 (
b1111111111111110 &
b1111111111111101 '
b1111111111111101 +
b1111111111111110 %
b1111111111111110 *
#90
1G
1C
1;
0=
1>
1$
1Z"
1Q"
1H"
1?"
16"
1-"
1$"
1y
1p
1g
1^
1U
1L
1:
b11111111111111110 -
b0 !
b0 "
b0 ,
0F
1D
0O
1P
1M
0X
1Y
1V
0a
1b
1_
0j
1k
1h
0s
1t
1q
0|
1}
1z
0'"
1("
1%"
00"
11"
1."
09"
1:"
17"
0B"
1C"
1@"
0K"
1L"
1I"
0T"
1U"
1R"
0]"
1^"
1["
04
12
1E
0H
1N
0Q
1W
0Z
1`
0c
1i
0l
1r
0u
1{
0~
1&"
0)"
1/"
02"
18"
0;"
1A"
0D"
1J"
0M"
1S"
0V"
1\"
0_"
03
16
0B
0K
0T
0]
0f
0o
0x
0#"
0,"
05"
0>"
0G"
0P"
0Y"
1/
b1 (
b1111111111111111 &
b1 '
b1 +
b1111111111111111 %
b1111111111111111 *
#100
b1111111111111110 !
b1111111111111110 "
b1111111111111110 ,
1=
0>
1F
0G
1O
0P
1X
0Y
1a
0b
1j
0k
1s
0t
1|
0}
1'"
0("
10"
01"
19"
0:"
1B"
0C"
1K"
0L"
1T"
0U"
1]"
0^"
0#
0<
1?
0E
1H
0N
1Q
0W
1Z
0`
1c
0i
1l
0r
1u
0{
1~
0&"
1)"
0/"
12"
08"
1;"
0A"
1D"
0J"
1M"
0S"
1V"
0\"
1_"
19
1B
1K
1T
1]
1f
1o
1x
1#"
1,"
15"
1>"
1G"
1P"
1Y"
b1111111111111111 (
b1111111111111111 '
b1111111111111111 +
