Full_Adder/Full_Adder_4bit/half_adder.v
module half_adder(
    input a,
    input b,
    output sum,
    output carry
);
    
    // Logic for sum (XOR operation)
    assign sum = a ^ b;
    
    // Logic for carry (AND operation)
    assign carry = a & b;
    
endmodule

Full_Adder/Full_Adder_32bit/full_adder_1bit.v
module full_adder_1bit(
	input a,
	input b,
	input cin,
	output sum,
	output cout
);
	wire sum1;
	wire carry1;
	wire carry2;
	
	half_adder ha1(
               .a(a),
		       .b(b),
		       .sum(sum1),
		       .carry(carry1)
	);
	
	half_adder ha2(
               .a(sum1),
		       .b(cin),
		       .sum(sum),
		       .carry(carry2) 		
	);

	assign cout = carry1 | carry2;
endmodule

Full_Adder/Full_Adder_4bit/full_adder_4bit.v
module full_adder_4bit(
    input [3:0] a,
    input [3:0] b,
    input cin,
    output [3:0] sum,
    output cout,
    output overflow
);
    wire sum1;
    wire sum2;
    wire sum3;
    wire sum4;
    wire carry1;
    wire carry2;
    wire carry3;

    full_adder_1bit fa1(
        .a(a[0]),
        .b(b[0]),
        .cin(cin),
        .sum(sum[0]),
        .cout(carry1)
    );
    
    full_adder_1bit fa2(
        .a(a[1]),
        .b(b[1]),
        .cin(carry1),
        .sum(sum[1]),
        .cout(carry2)
    );

    full_adder_1bit fa3(
        .a(a[2]),
        .b(b[2]),
        .cin(carry2),
        .sum(sum[2]),
        .cout(carry3)
    );

    full_adder_1bit fa4(
        .a(a[3]),
        .b(b[3]),
        .cin(carry3),
        .sum(sum[3]),
        .cout(cout)
    );
    
    // Overflow xảy ra khi hai số cùng dấu nhưng kết quả khác dấu
    // Đối với số có dấu (signed numbers)
    assign overflow = (a[3] == b[3]) && (a[3] != sum[3]);
endmodule

Full_Adder/Full_Adder_4bit/full_adder_4bit_tb.v
module full_adder_4bit_tb;
    // Inputs
    reg [3:0] a;
    reg [3:0] b;
    reg cin;
    
    // Outputs
    wire [3:0] sum;
    wire cout;
    wire overflow;
    
    // Biến phụ để hiển thị số có dấu
    reg signed [3:0] a_signed;
    reg signed [3:0] b_signed;
    wire signed [3:0] sum_signed;
    
    // Instantiate the Unit Under Test (UUT)
    full_adder_4bit uut (
        .a(a),
        .b(b),
        .cin(cin),
        .sum(sum),
        .cout(cout),
        .overflow(overflow)
    );
    
    // Gán giá trị cho biến phụ
    always @* begin
        a_signed = a;
        b_signed = b;
    end
    
    assign sum_signed = sum;
    
    initial begin
        // Initialize inputs
        a = 0; b = 0; cin = 0;
        #10;
        
        // Test case 1: Simple addition (không tràn số)
        a = 4'b0001; b = 4'b0001; cin = 0; // 1 + 1 = 2
        #10;
        
        // Test case 2: Addition with carry-in (không tràn số)
        a = 4'b0001; b = 4'b0001; cin = 1; // 1 + 1 + 1 = 3
        #10;
        
        // Test case 3: Larger numbers (không tràn số với unsigned, tràn số với signed)
        a = 4'b0011; b = 4'b0101; cin = 0; // 3 + 5 = 8 (unsigned) hoặc -8 (signed)
        #10;
        
        // Test case 4: Generate carry-out (tràn số dương)
        a = 4'b0111; b = 4'b0001; cin = 0; // 7 + 1 = 8 (unsigned) hoặc -8 (signed)
        #10;
        
        // Test case 5: Maximum unsigned value
        a = 4'b1111; b = 4'b1111; cin = 0; // 15 + 15 = 30 (cout=1, sum=1110)
        #10;
        
        // Test case 6: Maximum unsigned value with carry-in
        a = 4'b1111; b = 4'b1111; cin = 1; // 15 + 15 + 1 = 31 (cout=1, sum=1111)
        #10;
        
        // Test case 7: Negative numbers (tràn số âm)
        a = 4'b1000; b = 4'b1000; cin = 0; // -8 + -8 = -16 (vượt quá phạm vi biểu diễn)
        #10;
        
        // Test case 8: Positive + Negative (không tràn số)
        a = 4'b0111; b = 4'b1001; cin = 0; // 7 + -7 = 0
        #10;
        
        $finish;
    end
    
    // Display results
    initial begin
        $monitor("Time=%0t | a=%b(%0d/%0d) b=%b(%0d/%0d) cin=%b | sum=%b(%0d/%0d) cout=%b overflow=%b", 
                 $time, a, a, a_signed, b, b, b_signed, cin, sum, sum, sum_signed, cout, overflow);
        $dumpfile("full_adder_4bit_tb.vcd");
        $dumpvars(0, full_adder_4bit_tb);
    end
endmodule

Full_Adder/Full_Adder_4bit/full_adder_4bit_tb.vcd
$date
	Mon Jun 23 13:44:30 2025
$end
$version
	Icarus Verilog
$end
$timescale
	1s
$end
$scope module full_adder_4bit_tb $end
$var wire 4 ! sum_signed [3:0] $end
$var wire 4 " sum [3:0] $end
$var wire 1 # overflow $end
$var wire 1 $ cout $end
$var reg 4 % a [3:0] $end
$var reg 4 & a_signed [3:0] $end
$var reg 4 ' b [3:0] $end
$var reg 4 ( b_signed [3:0] $end
$var reg 1 ) cin $end
$scope module uut $end
$var wire 4 * a [3:0] $end
$var wire 4 + b [3:0] $end
$var wire 1 ) cin $end
$var wire 1 # overflow $end
$var wire 4 , sum [3:0] $end
$var wire 1 $ cout $end
$var wire 1 - carry3 $end
$var wire 1 . carry2 $end
$var wire 1 / carry1 $end
$scope module fa1 $end
$var wire 1 0 a $end
$var wire 1 1 b $end
$var wire 1 ) cin $end
$var wire 1 / cout $end
$var wire 1 2 sum1 $end
$var wire 1 3 sum $end
$var wire 1 4 carry2 $end
$var wire 1 5 carry1 $end
$scope module ha1 $end
$var wire 1 0 a $end
$var wire 1 1 b $end
$var wire 1 5 carry $end
$var wire 1 2 sum $end
$upscope $end
$scope module ha2 $end
$var wire 1 2 a $end
$var wire 1 ) b $end
$var wire 1 4 carry $end
$var wire 1 3 sum $end
$upscope $end
$upscope $end
$scope module fa2 $end
$var wire 1 6 a $end
$var wire 1 7 b $end
$var wire 1 / cin $end
$var wire 1 . cout $end
$var wire 1 8 sum1 $end
$var wire 1 9 sum $end
$var wire 1 : carry2 $end
$var wire 1 ; carry1 $end
$scope module ha1 $end
$var wire 1 6 a $end
$var wire 1 7 b $end
$var wire 1 ; carry $end
$var wire 1 8 sum $end
$upscope $end
$scope module ha2 $end
$var wire 1 8 a $end
$var wire 1 / b $end
$var wire 1 : carry $end
$var wire 1 9 sum $end
$upscope $end
$upscope $end
$scope module fa3 $end
$var wire 1 < a $end
$var wire 1 = b $end
$var wire 1 . cin $end
$var wire 1 - cout $end
$var wire 1 > sum1 $end
$var wire 1 ? sum $end
$var wire 1 @ carry2 $end
$var wire 1 A carry1 $end
$scope module ha1 $end
$var wire 1 < a $end
$var wire 1 = b $end
$var wire 1 A carry $end
$var wire 1 > sum $end
$upscope $end
$scope module ha2 $end
$var wire 1 > a $end
$var wire 1 . b $end
$var wire 1 @ carry $end
$var wire 1 ? sum $end
$upscope $end
$upscope $end
$scope module fa4 $end
$var wire 1 B a $end
$var wire 1 C b $end
$var wire 1 - cin $end
$var wire 1 $ cout $end
$var wire 1 D sum1 $end
$var wire 1 E sum $end
$var wire 1 F carry2 $end
$var wire 1 G carry1 $end
$scope module ha1 $end
$var wire 1 B a $end
$var wire 1 C b $end
$var wire 1 G carry $end
$var wire 1 D sum $end
$upscope $end
$scope module ha2 $end
$var wire 1 D a $end
$var wire 1 - b $end
$var wire 1 F carry $end
$var wire 1 E sum $end
$upscope $end
$upscope $end
$upscope $end
$upscope $end
$enddefinitions $end
$comment Show the parameter values. $end
$dumpall
$end
#0
$dumpvars
0G
0F
0E
0D
0C
0B
0A
0@
0?
0>
0=
0<
0;
0:
09
08
07
06
05
04
03
02
01
00
0/
0.
0-
b0 ,
b0 +
b0 *
0)
b0 (
b0 '
b0 &
b0 %
0$
0#
b0 "
b0 !
$end
#10
b10 !
b10 "
b10 ,
19
1/
15
11
10
b1 (
b1 &
b1 '
b1 +
b1 %
b1 *
#20
b11 !
b11 "
b11 ,
13
1)
#30
1#
1E
1-
1@
1.
0?
09
1:
b1000 !
b1000 "
b1000 ,
1>
18
03
1=
16
b101 (
b11 &
0)
b101 '
b101 +
b11 %
b11 *
#40
0=
1<
b1 (
b111 &
b1 '
b1 +
b111 %
b111 *
#50
b1110 !
b1110 "
b1110 ,
19
0:
1?
0@
1$
0#
08
1;
0>
1A
1G
17
1=
1C
1B
b1111 (
b1111 &
b1111 '
b1111 +
b1111 %
b1111 *
#60
b1111 !
b1111 "
b1111 ,
13
1)
#70
1#
09
0?
0E
0/
0.
0-
b0 !
b0 "
b0 ,
05
0;
0A
03
01
07
0=
00
06
0<
b1000 (
b1000 &
0)
b1000 '
b1000 +
b1000 %
b1000 *
#80
1F
1-
1@
1.
1:
b0 !
b0 "
b0 ,
1/
09
0?
0E
1$
0#
15
18
1>
1D
0G
11
10
16
1<
0B
b1001 (
b111 &
b1001 '
b1001 +
b111 %
b111 *
